ngraph_onnx/__init__.py
ngraph_onnx/onnx_importer/__init__.py
ngraph_onnx/onnx_importer/backend.py
ngraph_onnx/onnx_importer/importer.py
ngraph_onnx/onnx_importer/utils/__init__.py
ngraph_onnx/onnx_importer/utils/types.py
ngraph_onnx-0.24.0.data/data/LICENSE
ngraph_onnx-0.24.0.data/data/licenses/cachetools-license.txt
ngraph_onnx-0.24.0.data/data/licenses/numpy-license.txt
ngraph_onnx-0.24.0.data/data/licenses/onnx-license.txt
ngraph_onnx-0.24.0.dist-info/LICENSE
ngraph_onnx-0.24.0.dist-info/METADATA
ngraph_onnx-0.24.0.dist-info/WHEEL
ngraph_onnx-0.24.0.dist-info/top_level.txt
ngraph_onnx-0.24.0.dist-info/RECORD
