Metadata-Version: 2.1
Name: ngraph-onnx
Version: 0.24.0
Summary: nGraph Backend for ONNX
Home-page: https://github.com/NervanaSystems/ngraph-onnx
Author: Intel
Author-email: intelnervana@intel.com
License: License :: OSI Approved :: Apache Software License
Platform: UNKNOWN
Requires-Dist: cachetools
Requires-Dist: ngraph-core
Requires-Dist: numpy
Requires-Dist: onnx
Requires-Dist: setuptools
